{
  "openapi": "3.0.1",
  "info": {
    "title": "AttendMe backend",
    "version": "0.1.0"
  },
  "paths": {
    "/attendergroup/save": {
      "post": {
        "tags": [
          "AttenderGroup"
        ],
        "requestBody": {
          "content": {
            "application/json": {
              "schema": {
                "$ref": "#/components/schemas/AttenderGroup"
              }
            },
            "text/json": {
              "schema": {
                "$ref": "#/components/schemas/AttenderGroup"
              }
            },
            "application/*+json": {
              "schema": {
                "$ref": "#/components/schemas/AttenderGroup"
              }
            }
          }
        },
        "responses": {
          "200": {
            "description": "Success",
            "content": {
              "text/plain": {
                "schema": {
                  "$ref": "#/components/schemas/AttenderGroup"
                }
              },
              "application/json": {
                "schema": {
                  "$ref": "#/components/schemas/AttenderGroup"
                }
              },
              "text/json": {
                "schema": {
                  "$ref": "#/components/schemas/AttenderGroup"
                }
              }
            }
          },
          "403": {
            "description": "Forbidden",
            "content": {
              "text/plain": {
                "schema": {
                  "$ref": "#/components/schemas/ProblemDetails"
                }
              },
              "application/json": {
                "schema": {
                  "$ref": "#/components/schemas/ProblemDetails"
                }
              },
              "text/json": {
                "schema": {
                  "$ref": "#/components/schemas/ProblemDetails"
                }
              }
            }
          }
        }
      }
    },
    "/attendergroup/member/add": {
      "post": {
        "tags": [
          "AttenderGroup"
        ],
        "parameters": [
          {
            "name": "attenderGroupId",
            "in": "query",
            "schema": {
              "type": "integer",
              "format": "int32"
            }
          },
          {
            "name": "userId",
            "in": "query",
            "schema": {
              "type": "integer",
              "format": "int32"
            }
          }
        ],
        "responses": {
          "200": {
            "description": "Success",
            "content": {
              "text/plain": {
                "schema": {
                  "$ref": "#/components/schemas/AttenderGroup"
                }
              },
              "application/json": {
                "schema": {
                  "$ref": "#/components/schemas/AttenderGroup"
                }
              },
              "text/json": {
                "schema": {
                  "$ref": "#/components/schemas/AttenderGroup"
                }
              }
            }
          },
          "403": {
            "description": "Forbidden",
            "content": {
              "text/plain": {
                "schema": {
                  "$ref": "#/components/schemas/ProblemDetails"
                }
              },
              "application/json": {
                "schema": {
                  "$ref": "#/components/schemas/ProblemDetails"
                }
              },
              "text/json": {
                "schema": {
                  "$ref": "#/components/schemas/ProblemDetails"
                }
              }
            }
          }
        }
      }
    },
    "/course/save": {
      "post": {
        "tags": [
          "Course"
        ],
        "requestBody": {
          "content": {
            "application/json": {
              "schema": {
                "$ref": "#/components/schemas/Course"
              }
            },
            "text/json": {
              "schema": {
                "$ref": "#/components/schemas/Course"
              }
            },
            "application/*+json": {
              "schema": {
                "$ref": "#/components/schemas/Course"
              }
            }
          }
        },
        "responses": {
          "200": {
            "description": "Success",
            "content": {
              "text/plain": {
                "schema": {
                  "$ref": "#/components/schemas/Course"
                }
              },
              "application/json": {
                "schema": {
                  "$ref": "#/components/schemas/Course"
                }
              },
              "text/json": {
                "schema": {
                  "$ref": "#/components/schemas/Course"
                }
              }
            }
          },
          "403": {
            "description": "Forbidden",
            "content": {
              "text/plain": {
                "schema": {
                  "$ref": "#/components/schemas/ProblemDetails"
                }
              },
              "application/json": {
                "schema": {
                  "$ref": "#/components/schemas/ProblemDetails"
                }
              },
              "text/json": {
                "schema": {
                  "$ref": "#/components/schemas/ProblemDetails"
                }
              }
            }
          }
        }
      }
    },
    "/course/group/save": {
      "post": {
        "tags": [
          "Course"
        ],
        "requestBody": {
          "content": {
            "application/json": {
              "schema": {
                "$ref": "#/components/schemas/CourseGroup"
              }
            },
            "text/json": {
              "schema": {
                "$ref": "#/components/schemas/CourseGroup"
              }
            },
            "application/*+json": {
              "schema": {
                "$ref": "#/components/schemas/CourseGroup"
              }
            }
          }
        },
        "responses": {
          "200": {
            "description": "Success",
            "content": {
              "text/plain": {
                "schema": {
                  "$ref": "#/components/schemas/CourseGroup"
                }
              },
              "application/json": {
                "schema": {
                  "$ref": "#/components/schemas/CourseGroup"
                }
              },
              "text/json": {
                "schema": {
                  "$ref": "#/components/schemas/CourseGroup"
                }
              }
            }
          },
          "403": {
            "description": "Forbidden",
            "content": {
              "text/plain": {
                "schema": {
                  "$ref": "#/components/schemas/ProblemDetails"
                }
              },
              "application/json": {
                "schema": {
                  "$ref": "#/components/schemas/ProblemDetails"
                }
              },
              "text/json": {
                "schema": {
                  "$ref": "#/components/schemas/ProblemDetails"
                }
              }
            }
          }
        }
      }
    },
    "/course/group/attender-user/add": {
      "post": {
        "tags": [
          "Course"
        ],
        "parameters": [
          {
            "name": "courseGroupId",
            "in": "query",
            "schema": {
              "type": "integer",
              "format": "int32"
            }
          },
          {
            "name": "userId",
            "in": "query",
            "schema": {
              "type": "integer",
              "format": "int32"
            }
          }
        ],
        "responses": {
          "200": {
            "description": "Success"
          },
          "403": {
            "description": "Forbidden",
            "content": {
              "text/plain": {
                "schema": {
                  "$ref": "#/components/schemas/ProblemDetails"
                }
              },
              "application/json": {
                "schema": {
                  "$ref": "#/components/schemas/ProblemDetails"
                }
              },
              "text/json": {
                "schema": {
                  "$ref": "#/components/schemas/ProblemDetails"
                }
              }
            }
          }
        }
      }
    },
    "/course/group/attender-group/add": {
      "post": {
        "tags": [
          "Course"
        ],
        "parameters": [
          {
            "name": "courseGroupId",
            "in": "query",
            "schema": {
              "type": "integer",
              "format": "int32"
            }
          },
          {
            "name": "AttenderGroupId",
            "in": "query",
            "schema": {
              "type": "integer",
              "format": "int32"
            }
          }
        ],
        "responses": {
          "200": {
            "description": "Success"
          },
          "403": {
            "description": "Forbidden",
            "content": {
              "text/plain": {
                "schema": {
                  "$ref": "#/components/schemas/ProblemDetails"
                }
              },
              "application/json": {
                "schema": {
                  "$ref": "#/components/schemas/ProblemDetails"
                }
              },
              "text/json": {
                "schema": {
                  "$ref": "#/components/schemas/ProblemDetails"
                }
              }
            }
          }
        }
      }
    },
    "/course/group/teacher/assign": {
      "post": {
        "tags": [
          "Course"
        ],
        "parameters": [
          {
            "name": "courseGroupId",
            "in": "query",
            "schema": {
              "type": "integer",
              "format": "int32"
            }
          },
          {
            "name": "teacherUserId",
            "in": "query",
            "schema": {
              "type": "integer",
              "format": "int32"
            }
          }
        ],
        "responses": {
          "200": {
            "description": "Success"
          },
          "403": {
            "description": "Forbidden",
            "content": {
              "text/plain": {
                "schema": {
                  "$ref": "#/components/schemas/ProblemDetails"
                }
              },
              "application/json": {
                "schema": {
                  "$ref": "#/components/schemas/ProblemDetails"
                }
              },
              "text/json": {
                "schema": {
                  "$ref": "#/components/schemas/ProblemDetails"
                }
              }
            }
          }
        }
      }
    },
    "/course/teacher/session/get": {
      "get": {
        "tags": [
          "Course"
        ],
        "parameters": [
          {
            "name": "sessionId",
            "in": "query",
            "schema": {
              "type": "integer",
              "format": "int32"
            }
          }
        ],
        "responses": {
          "200": {
            "description": "Success",
            "content": {
              "text/plain": {
                "schema": {
                  "$ref": "#/components/schemas/CourseSessionListItem"
                }
              },
              "application/json": {
                "schema": {
                  "$ref": "#/components/schemas/CourseSessionListItem"
                }
              },
              "text/json": {
                "schema": {
                  "$ref": "#/components/schemas/CourseSessionListItem"
                }
              }
            }
          },
          "403": {
            "description": "Forbidden",
            "content": {
              "text/plain": {
                "schema": {
                  "$ref": "#/components/schemas/ProblemDetails"
                }
              },
              "application/json": {
                "schema": {
                  "$ref": "#/components/schemas/ProblemDetails"
                }
              },
              "text/json": {
                "schema": {
                  "$ref": "#/components/schemas/ProblemDetails"
                }
              }
            }
          }
        }
      }
    },
    "/course/student/group/sessions/get": {
      "get": {
        "tags": [
          "Course"
        ],
        "parameters": [
          {
            "name": "courseGroupId",
            "in": "query",
            "schema": {
              "type": "integer",
              "format": "int32"
            }
          }
        ],
        "responses": {
          "200": {
            "description": "Success",
            "content": {
              "text/plain": {
                "schema": {
                  "type": "array",
                  "items": {
                    "$ref": "#/components/schemas/CourseSessionListItem"
                  }
                }
              },
              "application/json": {
                "schema": {
                  "type": "array",
                  "items": {
                    "$ref": "#/components/schemas/CourseSessionListItem"
                  }
                }
              },
              "text/json": {
                "schema": {
                  "type": "array",
                  "items": {
                    "$ref": "#/components/schemas/CourseSessionListItem"
                  }
                }
              }
            }
          },
          "403": {
            "description": "Forbidden",
            "content": {
              "text/plain": {
                "schema": {
                  "$ref": "#/components/schemas/ProblemDetails"
                }
              },
              "application/json": {
                "schema": {
                  "$ref": "#/components/schemas/ProblemDetails"
                }
              },
              "text/json": {
                "schema": {
                  "$ref": "#/components/schemas/ProblemDetails"
                }
              }
            }
          }
        }
      }
    },
    "/course/student/attendance/get": {
      "get": {
        "tags": [
          "Course"
        ],
        "parameters": [
          {
            "name": "courseGroupId",
            "in": "query",
            "schema": {
              "type": "integer",
              "format": "int32"
            }
          }
        ],
        "responses": {
          "200": {
            "description": "Success",
            "content": {
              "text/plain": {
                "schema": {
                  "type": "array",
                  "items": {
                    "$ref": "#/components/schemas/AttendanceLog"
                  }
                }
              },
              "application/json": {
                "schema": {
                  "type": "array",
                  "items": {
                    "$ref": "#/components/schemas/AttendanceLog"
                  }
                }
              },
              "text/json": {
                "schema": {
                  "type": "array",
                  "items": {
                    "$ref": "#/components/schemas/AttendanceLog"
                  }
                }
              }
            }
          },
          "403": {
            "description": "Forbidden",
            "content": {
              "text/plain": {
                "schema": {
                  "$ref": "#/components/schemas/ProblemDetails"
                }
              },
              "application/json": {
                "schema": {
                  "$ref": "#/components/schemas/ProblemDetails"
                }
              },
              "text/json": {
                "schema": {
                  "$ref": "#/components/schemas/ProblemDetails"
                }
              }
            }
          }
        }
      }
    },
    "/course/session/save": {
      "post": {
        "tags": [
          "Course"
        ],
        "requestBody": {
          "content": {
            "application/json": {
              "schema": {
                "$ref": "#/components/schemas/CourseSession"
              }
            },
            "text/json": {
              "schema": {
                "$ref": "#/components/schemas/CourseSession"
              }
            },
            "application/*+json": {
              "schema": {
                "$ref": "#/components/schemas/CourseSession"
              }
            }
          }
        },
        "responses": {
          "200": {
            "description": "Success",
            "content": {
              "text/plain": {
                "schema": {
                  "$ref": "#/components/schemas/CourseSession"
                }
              },
              "application/json": {
                "schema": {
                  "$ref": "#/components/schemas/CourseSession"
                }
              },
              "text/json": {
                "schema": {
                  "$ref": "#/components/schemas/CourseSession"
                }
              }
            }
          },
          "403": {
            "description": "Forbidden",
            "content": {
              "text/plain": {
                "schema": {
                  "$ref": "#/components/schemas/ProblemDetails"
                }
              },
              "application/json": {
                "schema": {
                  "$ref": "#/components/schemas/ProblemDetails"
                }
              },
              "text/json": {
                "schema": {
                  "$ref": "#/components/schemas/ProblemDetails"
                }
              }
            }
          }
        }
      }
    },
    "/course/student/sessions/get": {
      "post": {
        "tags": [
          "Course"
        ],
        "requestBody": {
          "content": {
            "application/json": {
              "schema": {
                "$ref": "#/components/schemas/CourseSessionListFiltersPagedListParams"
              }
            },
            "text/json": {
              "schema": {
                "$ref": "#/components/schemas/CourseSessionListFiltersPagedListParams"
              }
            },
            "application/*+json": {
              "schema": {
                "$ref": "#/components/schemas/CourseSessionListFiltersPagedListParams"
              }
            }
          }
        },
        "responses": {
          "200": {
            "description": "Success",
            "content": {
              "text/plain": {
                "schema": {
                  "$ref": "#/components/schemas/CourseSessionListItemPagedList"
                }
              },
              "application/json": {
                "schema": {
                  "$ref": "#/components/schemas/CourseSessionListItemPagedList"
                }
              },
              "text/json": {
                "schema": {
                  "$ref": "#/components/schemas/CourseSessionListItemPagedList"
                }
              }
            }
          }
        }
      }
    },
    "/course/teacher/sessions/get": {
      "post": {
        "tags": [
          "Course"
        ],
        "requestBody": {
          "content": {
            "application/json": {
              "schema": {
                "$ref": "#/components/schemas/CourseSessionListFiltersPagedListParams"
              }
            },
            "text/json": {
              "schema": {
                "$ref": "#/components/schemas/CourseSessionListFiltersPagedListParams"
              }
            },
            "application/*+json": {
              "schema": {
                "$ref": "#/components/schemas/CourseSessionListFiltersPagedListParams"
              }
            }
          }
        },
        "responses": {
          "200": {
            "description": "Success",
            "content": {
              "text/plain": {
                "schema": {
                  "$ref": "#/components/schemas/CourseSessionListItemPagedList"
                }
              },
              "application/json": {
                "schema": {
                  "$ref": "#/components/schemas/CourseSessionListItemPagedList"
                }
              },
              "text/json": {
                "schema": {
                  "$ref": "#/components/schemas/CourseSessionListItemPagedList"
                }
              }
            }
          }
        }
      }
    },
    "/course/session/attendance-list/get": {
      "get": {
        "tags": [
          "Course"
        ],
        "parameters": [
          {
            "name": "sessionId",
            "in": "query",
            "schema": {
              "type": "integer",
              "format": "int32"
            }
          }
        ],
        "responses": {
          "200": {
            "description": "Success",
            "content": {
              "text/plain": {
                "schema": {
                  "type": "array",
                  "items": {
                    "$ref": "#/components/schemas/CourseSessionAttendanceRecord"
                  }
                }
              },
              "application/json": {
                "schema": {
                  "type": "array",
                  "items": {
                    "$ref": "#/components/schemas/CourseSessionAttendanceRecord"
                  }
                }
              },
              "text/json": {
                "schema": {
                  "type": "array",
                  "items": {
                    "$ref": "#/components/schemas/CourseSessionAttendanceRecord"
                  }
                }
              }
            }
          }
        }
      }
    },
    "/course/session/attendance/scanner/token/get": {
      "get": {
        "tags": [
          "Course"
        ],
        "parameters": [
          {
            "name": "courseSessionId",
            "in": "query",
            "schema": {
              "type": "integer",
              "format": "int32"
            }
          }
        ],
        "responses": {
          "200": {
            "description": "Success",
            "content": {
              "text/plain": {
                "schema": {
                  "$ref": "#/components/schemas/TokenResult"
                }
              },
              "application/json": {
                "schema": {
                  "$ref": "#/components/schemas/TokenResult"
                }
              },
              "text/json": {
                "schema": {
                  "$ref": "#/components/schemas/TokenResult"
                }
              }
            }
          }
        }
      }
    },
    "/course/session/attendance/register": {
      "get": {
        "tags": [
          "Course"
        ],
        "parameters": [
          {
            "name": "attenderToken",
            "in": "query",
            "schema": {
              "type": "string"
            }
          }
        ],
        "responses": {
          "200": {
            "description": "Success",
            "content": {
              "text/plain": {
                "schema": {
                  "$ref": "#/components/schemas/User"
                }
              },
              "application/json": {
                "schema": {
                  "$ref": "#/components/schemas/User"
                }
              },
              "text/json": {
                "schema": {
                  "$ref": "#/components/schemas/User"
                }
              }
            }
          },
          "400": {
            "description": "Bad Request",
            "content": {
              "text/plain": {
                "schema": {
                  "$ref": "#/components/schemas/ProblemDetails"
                }
              },
              "application/json": {
                "schema": {
                  "$ref": "#/components/schemas/ProblemDetails"
                }
              },
              "text/json": {
                "schema": {
                  "$ref": "#/components/schemas/ProblemDetails"
                }
              }
            }
          },
          "403": {
            "description": "Forbidden",
            "content": {
              "text/plain": {
                "schema": {
                  "$ref": "#/components/schemas/ProblemDetails"
                }
              },
              "application/json": {
                "schema": {
                  "$ref": "#/components/schemas/ProblemDetails"
                }
              },
              "text/json": {
                "schema": {
                  "$ref": "#/components/schemas/ProblemDetails"
                }
              }
            }
          }
        }
      }
    },
    "/course/session/attendance/toggle": {
      "get": {
        "tags": [
          "Course"
        ],
        "parameters": [
          {
            "name": "attendingUserId",
            "in": "query",
            "schema": {
              "type": "integer",
              "format": "int32"
            }
          },
          {
            "name": "courseSessionId",
            "in": "query",
            "schema": {
              "type": "integer",
              "format": "int32"
            }
          },
          {
            "name": "addOrRemove",
            "in": "query",
            "schema": {
              "type": "boolean"
            }
          }
        ],
        "responses": {
          "200": {
            "description": "Success",
            "content": {
              "text/plain": {
                "schema": {
                  "type": "array",
                  "items": {
                    "$ref": "#/components/schemas/AttendanceLog"
                  }
                }
              },
              "application/json": {
                "schema": {
                  "type": "array",
                  "items": {
                    "$ref": "#/components/schemas/AttendanceLog"
                  }
                }
              },
              "text/json": {
                "schema": {
                  "type": "array",
                  "items": {
                    "$ref": "#/components/schemas/AttendanceLog"
                  }
                }
              }
            }
          },
          "400": {
            "description": "Bad Request",
            "content": {
              "text/plain": {
                "schema": {
                  "$ref": "#/components/schemas/ProblemDetails"
                }
              },
              "application/json": {
                "schema": {
                  "$ref": "#/components/schemas/ProblemDetails"
                }
              },
              "text/json": {
                "schema": {
                  "$ref": "#/components/schemas/ProblemDetails"
                }
              }
            }
          },
          "403": {
            "description": "Forbidden",
            "content": {
              "text/plain": {
                "schema": {
                  "$ref": "#/components/schemas/ProblemDetails"
                }
              },
              "application/json": {
                "schema": {
                  "$ref": "#/components/schemas/ProblemDetails"
                }
              },
              "text/json": {
                "schema": {
                  "$ref": "#/components/schemas/ProblemDetails"
                }
              }
            }
          }
        }
      }
    },
    "/test/token-decode": {
      "post": {
        "tags": [
          "Test"
        ],
        "parameters": [
          {
            "name": "token",
            "in": "query",
            "schema": {
              "type": "string"
            }
          }
        ],
        "responses": {
          "200": {
            "description": "Success",
            "content": {
              "text/plain": {
                "schema": {
                  "type": "string"
                }
              },
              "application/json": {
                "schema": {
                  "type": "string"
                }
              },
              "text/json": {
                "schema": {
                  "type": "string"
                }
              }
            }
          }
        }
      }
    },
    "/user/login": {
      "post": {
        "tags": [
          "User"
        ],
        "parameters": [
          {
            "name": "loginName",
            "in": "query",
            "schema": {
              "type": "string"
            }
          },
          {
            "name": "password",
            "in": "query",
            "schema": {
              "type": "string"
            }
          }
        ],
        "responses": {
          "200": {
            "description": "Success",
            "content": {
              "text/plain": {
                "schema": {
                  "$ref": "#/components/schemas/TokenResult"
                }
              },
              "application/json": {
                "schema": {
                  "$ref": "#/components/schemas/TokenResult"
                }
              },
              "text/json": {
                "schema": {
                  "$ref": "#/components/schemas/TokenResult"
                }
              }
            }
          }
        }
      }
    },
    "/user/device/reset": {
      "post": {
        "tags": [
          "User"
        ],
        "parameters": [
          {
            "name": "deviceUserId",
            "in": "query",
            "schema": {
              "type": "integer",
              "format": "int32"
            }
          }
        ],
        "responses": {
          "200": {
            "description": "Success"
          },
          "403": {
            "description": "Forbidden",
            "content": {
              "text/plain": {
                "schema": {
                  "$ref": "#/components/schemas/ProblemDetails"
                }
              },
              "application/json": {
                "schema": {
                  "$ref": "#/components/schemas/ProblemDetails"
                }
              },
              "text/json": {
                "schema": {
                  "$ref": "#/components/schemas/ProblemDetails"
                }
              }
            }
          }
        }
      }
    },
    "/user/device/register/token/get": {
      "get": {
        "tags": [
          "User"
        ],
        "parameters": [
          {
            "name": "deviceUserId",
            "in": "query",
            "schema": {
              "type": "integer",
              "format": "int32"
            }
          }
        ],
        "responses": {
          "200": {
            "description": "Success",
            "content": {
              "text/plain": {
                "schema": {
                  "$ref": "#/components/schemas/TokenResult"
                }
              },
              "application/json": {
                "schema": {
                  "$ref": "#/components/schemas/TokenResult"
                }
              },
              "text/json": {
                "schema": {
                  "$ref": "#/components/schemas/TokenResult"
                }
              }
            }
          },
          "403": {
            "description": "Forbidden",
            "content": {
              "text/plain": {
                "schema": {
                  "$ref": "#/components/schemas/ProblemDetails"
                }
              },
              "application/json": {
                "schema": {
                  "$ref": "#/components/schemas/ProblemDetails"
                }
              },
              "text/json": {
                "schema": {
                  "$ref": "#/components/schemas/ProblemDetails"
                }
              }
            }
          }
        }
      }
    },
    "/user/device/register": {
      "post": {
        "tags": [
          "User"
        ],
        "requestBody": {
          "content": {
            "application/json": {
              "schema": {
                "$ref": "#/components/schemas/DeviceRegisterDTO"
              }
            },
            "text/json": {
              "schema": {
                "$ref": "#/components/schemas/DeviceRegisterDTO"
              }
            },
            "application/*+json": {
              "schema": {
                "$ref": "#/components/schemas/DeviceRegisterDTO"
              }
            }
          }
        },
        "responses": {
          "200": {
            "description": "Success",
            "content": {
              "text/plain": {
                "schema": {
                  "$ref": "#/components/schemas/TokenResult"
                }
              },
              "application/json": {
                "schema": {
                  "$ref": "#/components/schemas/TokenResult"
                }
              },
              "text/json": {
                "schema": {
                  "$ref": "#/components/schemas/TokenResult"
                }
              }
            }
          },
          "403": {
            "description": "Forbidden",
            "content": {
              "text/plain": {
                "schema": {
                  "$ref": "#/components/schemas/ProblemDetails"
                }
              },
              "application/json": {
                "schema": {
                  "$ref": "#/components/schemas/ProblemDetails"
                }
              },
              "text/json": {
                "schema": {
                  "$ref": "#/components/schemas/ProblemDetails"
                }
              }
            }
          }
        }
      }
    },
    "/user/attendance/ticket/get": {
      "get": {
        "tags": [
          "User"
        ],
        "responses": {
          "200": {
            "description": "Success",
            "content": {
              "text/plain": {
                "schema": {
                  "$ref": "#/components/schemas/TokenResult"
                }
              },
              "application/json": {
                "schema": {
                  "$ref": "#/components/schemas/TokenResult"
                }
              },
              "text/json": {
                "schema": {
                  "$ref": "#/components/schemas/TokenResult"
                }
              }
            }
          }
        }
      }
    },
    "/user/get": {
      "get": {
        "tags": [
          "User"
        ],
        "parameters": [
          {
            "name": "userId",
            "in": "query",
            "schema": {
              "type": "integer",
              "format": "int32"
            }
          }
        ],
        "responses": {
          "200": {
            "description": "Success",
            "content": {
              "text/plain": {
                "schema": {
                  "$ref": "#/components/schemas/User"
                }
              },
              "application/json": {
                "schema": {
                  "$ref": "#/components/schemas/User"
                }
              },
              "text/json": {
                "schema": {
                  "$ref": "#/components/schemas/User"
                }
              }
            }
          },
          "403": {
            "description": "Forbidden",
            "content": {
              "text/plain": {
                "schema": {
                  "$ref": "#/components/schemas/ProblemDetails"
                }
              },
              "application/json": {
                "schema": {
                  "$ref": "#/components/schemas/ProblemDetails"
                }
              },
              "text/json": {
                "schema": {
                  "$ref": "#/components/schemas/ProblemDetails"
                }
              }
            }
          }
        }
      }
    },
    "/user/list/get": {
      "post": {
        "tags": [
          "User"
        ],
        "requestBody": {
          "content": {
            "application/json": {
              "schema": {
                "$ref": "#/components/schemas/UserListFiltersPagedListParams"
              }
            },
            "text/json": {
              "schema": {
                "$ref": "#/components/schemas/UserListFiltersPagedListParams"
              }
            },
            "application/*+json": {
              "schema": {
                "$ref": "#/components/schemas/UserListFiltersPagedListParams"
              }
            }
          }
        },
        "responses": {
          "403": {
            "description": "Forbidden",
            "content": {
              "text/plain": {
                "schema": {
                  "$ref": "#/components/schemas/ProblemDetails"
                }
              },
              "application/json": {
                "schema": {
                  "$ref": "#/components/schemas/ProblemDetails"
                }
              },
              "text/json": {
                "schema": {
                  "$ref": "#/components/schemas/ProblemDetails"
                }
              }
            }
          },
          "200": {
            "description": "Success",
            "content": {
              "text/plain": {
                "schema": {
                  "$ref": "#/components/schemas/UserListItemPagedList"
                }
              },
              "application/json": {
                "schema": {
                  "$ref": "#/components/schemas/UserListItemPagedList"
                }
              },
              "text/json": {
                "schema": {
                  "$ref": "#/components/schemas/UserListItemPagedList"
                }
              }
            }
          }
        }
      }
    },
    "/user/student/create": {
      "post": {
        "tags": [
          "User"
        ],
        "parameters": [
          {
            "name": "loginName",
            "in": "query",
            "schema": {
              "type": "string"
            }
          },
          {
            "name": "password",
            "in": "query",
            "schema": {
              "type": "string"
            }
          }
        ],
        "requestBody": {
          "content": {
            "application/json": {
              "schema": {
                "$ref": "#/components/schemas/StudentUserDTO"
              }
            },
            "text/json": {
              "schema": {
                "$ref": "#/components/schemas/StudentUserDTO"
              }
            },
            "application/*+json": {
              "schema": {
                "$ref": "#/components/schemas/StudentUserDTO"
              }
            }
          }
        },
        "responses": {
          "200": {
            "description": "Success",
            "content": {
              "text/plain": {
                "schema": {
                  "type": "integer",
                  "format": "int32"
                }
              },
              "application/json": {
                "schema": {
                  "type": "integer",
                  "format": "int32"
                }
              },
              "text/json": {
                "schema": {
                  "type": "integer",
                  "format": "int32"
                }
              }
            }
          },
          "403": {
            "description": "Forbidden",
            "content": {
              "text/plain": {
                "schema": {
                  "$ref": "#/components/schemas/ProblemDetails"
                }
              },
              "application/json": {
                "schema": {
                  "$ref": "#/components/schemas/ProblemDetails"
                }
              },
              "text/json": {
                "schema": {
                  "$ref": "#/components/schemas/ProblemDetails"
                }
              }
            }
          }
        }
      }
    },
    "/user/teacher/create": {
      "post": {
        "tags": [
          "User"
        ],
        "parameters": [
          {
            "name": "loginName",
            "in": "query",
            "schema": {
              "type": "string"
            }
          },
          {
            "name": "password",
            "in": "query",
            "schema": {
              "type": "string"
            }
          }
        ],
        "requestBody": {
          "content": {
            "application/json": {
              "schema": {
                "$ref": "#/components/schemas/TeacherUserDTO"
              }
            },
            "text/json": {
              "schema": {
                "$ref": "#/components/schemas/TeacherUserDTO"
              }
            },
            "application/*+json": {
              "schema": {
                "$ref": "#/components/schemas/TeacherUserDTO"
              }
            }
          }
        },
        "responses": {
          "200": {
            "description": "Success",
            "content": {
              "text/plain": {
                "schema": {
                  "type": "integer",
                  "format": "int32"
                }
              },
              "application/json": {
                "schema": {
                  "type": "integer",
                  "format": "int32"
                }
              },
              "text/json": {
                "schema": {
                  "type": "integer",
                  "format": "int32"
                }
              }
            }
          },
          "403": {
            "description": "Forbidden",
            "content": {
              "text/plain": {
                "schema": {
                  "$ref": "#/components/schemas/ProblemDetails"
                }
              },
              "application/json": {
                "schema": {
                  "$ref": "#/components/schemas/ProblemDetails"
                }
              },
              "text/json": {
                "schema": {
                  "$ref": "#/components/schemas/ProblemDetails"
                }
              }
            }
          }
        }
      }
    },
    "/user/admin/create": {
      "post": {
        "tags": [
          "User"
        ],
        "parameters": [
          {
            "name": "loginName",
            "in": "query",
            "schema": {
              "type": "string"
            }
          },
          {
            "name": "password",
            "in": "query",
            "schema": {
              "type": "string"
            }
          }
        ],
        "requestBody": {
          "content": {
            "application/json": {
              "schema": {
                "$ref": "#/components/schemas/UserDTO"
              }
            },
            "text/json": {
              "schema": {
                "$ref": "#/components/schemas/UserDTO"
              }
            },
            "application/*+json": {
              "schema": {
                "$ref": "#/components/schemas/UserDTO"
              }
            }
          }
        },
        "responses": {
          "200": {
            "description": "Success",
            "content": {
              "text/plain": {
                "schema": {
                  "type": "integer",
                  "format": "int32"
                }
              },
              "application/json": {
                "schema": {
                  "type": "integer",
                  "format": "int32"
                }
              },
              "text/json": {
                "schema": {
                  "type": "integer",
                  "format": "int32"
                }
              }
            }
          },
          "403": {
            "description": "Forbidden",
            "content": {
              "text/plain": {
                "schema": {
                  "$ref": "#/components/schemas/ProblemDetails"
                }
              },
              "application/json": {
                "schema": {
                  "$ref": "#/components/schemas/ProblemDetails"
                }
              },
              "text/json": {
                "schema": {
                  "$ref": "#/components/schemas/ProblemDetails"
                }
              }
            }
          }
        }
      }
    },
    "/user/update": {
      "put": {
        "tags": [
          "User"
        ],
        "parameters": [
          {
            "name": "userId",
            "in": "query",
            "schema": {
              "type": "integer",
              "format": "int32"
            }
          }
        ],
        "requestBody": {
          "content": {
            "application/json": {
              "schema": {
                "$ref": "#/components/schemas/UserDTO"
              }
            },
            "text/json": {
              "schema": {
                "$ref": "#/components/schemas/UserDTO"
              }
            },
            "application/*+json": {
              "schema": {
                "$ref": "#/components/schemas/UserDTO"
              }
            }
          }
        },
        "responses": {
          "200": {
            "description": "Success",
            "content": {
              "text/plain": {
                "schema": {
                  "type": "integer",
                  "format": "int32"
                }
              },
              "application/json": {
                "schema": {
                  "type": "integer",
                  "format": "int32"
                }
              },
              "text/json": {
                "schema": {
                  "type": "integer",
                  "format": "int32"
                }
              }
            }
          },
          "403": {
            "description": "Forbidden",
            "content": {
              "text/plain": {
                "schema": {
                  "$ref": "#/components/schemas/ProblemDetails"
                }
              },
              "application/json": {
                "schema": {
                  "$ref": "#/components/schemas/ProblemDetails"
                }
              },
              "text/json": {
                "schema": {
                  "$ref": "#/components/schemas/ProblemDetails"
                }
              }
            }
          },
          "404": {
            "description": "Not Found",
            "content": {
              "text/plain": {
                "schema": {
                  "$ref": "#/components/schemas/ProblemDetails"
                }
              },
              "application/json": {
                "schema": {
                  "$ref": "#/components/schemas/ProblemDetails"
                }
              },
              "text/json": {
                "schema": {
                  "$ref": "#/components/schemas/ProblemDetails"
                }
              }
            }
          }
        }
      }
    },
    "/user/student/update": {
      "put": {
        "tags": [
          "User"
        ],
        "parameters": [
          {
            "name": "userId",
            "in": "query",
            "schema": {
              "type": "integer",
              "format": "int32"
            }
          }
        ],
        "requestBody": {
          "content": {
            "application/json": {
              "schema": {
                "$ref": "#/components/schemas/StudentUserDTO"
              }
            },
            "text/json": {
              "schema": {
                "$ref": "#/components/schemas/StudentUserDTO"
              }
            },
            "application/*+json": {
              "schema": {
                "$ref": "#/components/schemas/StudentUserDTO"
              }
            }
          }
        },
        "responses": {
          "200": {
            "description": "Success",
            "content": {
              "text/plain": {
                "schema": {
                  "type": "integer",
                  "format": "int32"
                }
              },
              "application/json": {
                "schema": {
                  "type": "integer",
                  "format": "int32"
                }
              },
              "text/json": {
                "schema": {
                  "type": "integer",
                  "format": "int32"
                }
              }
            }
          },
          "403": {
            "description": "Forbidden",
            "content": {
              "text/plain": {
                "schema": {
                  "$ref": "#/components/schemas/ProblemDetails"
                }
              },
              "application/json": {
                "schema": {
                  "$ref": "#/components/schemas/ProblemDetails"
                }
              },
              "text/json": {
                "schema": {
                  "$ref": "#/components/schemas/ProblemDetails"
                }
              }
            }
          },
          "404": {
            "description": "Not Found",
            "content": {
              "text/plain": {
                "schema": {
                  "$ref": "#/components/schemas/ProblemDetails"
                }
              },
              "application/json": {
                "schema": {
                  "$ref": "#/components/schemas/ProblemDetails"
                }
              },
              "text/json": {
                "schema": {
                  "$ref": "#/components/schemas/ProblemDetails"
                }
              }
            }
          }
        }
      }
    },
    "/user/teacher/update": {
      "put": {
        "tags": [
          "User"
        ],
        "parameters": [
          {
            "name": "userId",
            "in": "query",
            "schema": {
              "type": "integer",
              "format": "int32"
            }
          }
        ],
        "requestBody": {
          "content": {
            "application/json": {
              "schema": {
                "$ref": "#/components/schemas/TeacherUserDTO"
              }
            },
            "text/json": {
              "schema": {
                "$ref": "#/components/schemas/TeacherUserDTO"
              }
            },
            "application/*+json": {
              "schema": {
                "$ref": "#/components/schemas/TeacherUserDTO"
              }
            }
          }
        },
        "responses": {
          "200": {
            "description": "Success",
            "content": {
              "text/plain": {
                "schema": {
                  "type": "integer",
                  "format": "int32"
                }
              },
              "application/json": {
                "schema": {
                  "type": "integer",
                  "format": "int32"
                }
              },
              "text/json": {
                "schema": {
                  "type": "integer",
                  "format": "int32"
                }
              }
            }
          },
          "403": {
            "description": "Forbidden",
            "content": {
              "text/plain": {
                "schema": {
                  "$ref": "#/components/schemas/ProblemDetails"
                }
              },
              "application/json": {
                "schema": {
                  "$ref": "#/components/schemas/ProblemDetails"
                }
              },
              "text/json": {
                "schema": {
                  "$ref": "#/components/schemas/ProblemDetails"
                }
              }
            }
          },
          "404": {
            "description": "Not Found",
            "content": {
              "text/plain": {
                "schema": {
                  "$ref": "#/components/schemas/ProblemDetails"
                }
              },
              "application/json": {
                "schema": {
                  "$ref": "#/components/schemas/ProblemDetails"
                }
              },
              "text/json": {
                "schema": {
                  "$ref": "#/components/schemas/ProblemDetails"
                }
              }
            }
          }
        }
      }
    }
  },
  "components": {
    "schemas": {
      "AttendanceLog": {
        "type": "object",
        "properties": {
          "attendanceLogId": {
            "type": "integer",
            "format": "int32"
          },
          "attenderUserId": {
            "type": "integer",
            "format": "int32"
          },
          "courseSessionId": {
            "type": "integer",
            "format": "int32"
          },
          "dateCreated": {
            "type": "string",
            "format": "date-time",
            "readOnly": true
          }
        },
        "additionalProperties": false
      },
      "AttenderGroup": {
        "type": "object",
        "properties": {
          "attenderGroupId": {
            "type": "integer",
            "format": "int32"
          },
          "groupName": {
            "maxLength": 255,
            "type": "string"
          },
          "yearOfStudy": {
            "type": "integer",
            "format": "int32"
          },
          "studyDirection": {
            "maxLength": 255,
            "type": "string"
          },
          "dateCreated": {
            "type": "string",
            "format": "date-time",
            "readOnly": true
          },
          "attenderGroupMembers": {
            "type": "array",
            "items": {
              "$ref": "#/components/schemas/AttenderGroupMember"
            },
            "nullable": true
          }
        },
        "additionalProperties": false
      },
      "AttenderGroupMember": {
        "type": "object",
        "properties": {
          "attenderGroupMemberId": {
            "type": "integer",
            "format": "int32"
          },
          "memberUserId": {
            "type": "integer",
            "format": "int32"
          },
          "memberUser": {
            "$ref": "#/components/schemas/User"
          },
          "attenderGroupId": {
            "type": "integer",
            "format": "int32"
          },
          "attenderGroup": {
            "$ref": "#/components/schemas/AttenderGroup"
          },
          "dateCreated": {
            "type": "string",
            "format": "date-time",
            "readOnly": true
          }
        },
        "additionalProperties": false
      },
      "Course": {
        "type": "object",
        "properties": {
          "courseId": {
            "type": "integer",
            "format": "int32"
          },
          "courseName": {
            "maxLength": 255,
            "type": "string"
          },
          "courseDescription": {
            "maxLength": 1024,
            "type": "string"
          },
          "dateCreated": {
            "type": "string",
            "format": "date-time",
            "readOnly": true
          },
          "courseGroups": {
            "type": "array",
            "items": {
              "$ref": "#/components/schemas/CourseGroup"
            },
            "nullable": true
          }
        },
        "additionalProperties": false
      },
      "CourseGroup": {
        "type": "object",
        "properties": {
          "courseGroupId": {
            "type": "integer",
            "format": "int32"
          },
          "courseId": {
            "type": "integer",
            "format": "int32"
          },
          "course": {
            "$ref": "#/components/schemas/Course"
          },
          "courseGroupType": {
            "maxLength": 32,
            "type": "string"
          },
          "courseGroupName": {
            "maxLength": 255,
            "type": "string"
          },
          "courseGroupDescription": {
            "maxLength": 1024,
            "type": "string",
            "nullable": true
          },
          "teacherUserId": {
            "type": "integer",
            "format": "int32",
            "nullable": true
          },
          "teacherUser": {
            "$ref": "#/components/schemas/User"
          },
          "sessions": {
            "type": "array",
            "items": {
              "$ref": "#/components/schemas/CourseSession"
            },
            "nullable": true
          },
          "attenderGroupAssigments": {
            "type": "array",
            "items": {
              "$ref": "#/components/schemas/CourseGroupAttenderGroupAssigment"
            },
            "nullable": true
          },
          "userAssigments": {
            "type": "array",
            "items": {
              "$ref": "#/components/schemas/CourseGroupUserAssigment"
            },
            "nullable": true
          },
          "yearOfStudy": {
            "type": "integer",
            "format": "int32"
          },
          "semesterCode": {
            "maxLength": 1024,
            "type": "string",
            "nullable": true
          },
          "dateStart": {
            "type": "string",
            "format": "date-time"
          },
          "dateEnd": {
            "type": "string",
            "format": "date-time"
          },
          "dateCreated": {
            "type": "string",
            "format": "date-time",
            "readOnly": true
          }
        },
        "additionalProperties": false
      },
      "CourseGroupAttenderGroupAssigment": {
        "type": "object",
        "properties": {
          "courseGroupAttenderGroupAssigmentId": {
            "type": "integer",
            "format": "int32"
          },
          "courseGroupId": {
            "type": "integer",
            "format": "int32"
          },
          "attenderGroupId": {
            "type": "integer",
            "format": "int32",
            "nullable": true
          },
          "isExcluded": {
            "type": "boolean"
          },
          "dateCreated": {
            "type": "string",
            "format": "date-time",
            "readOnly": true
          },
          "courseGroup": {
            "$ref": "#/components/schemas/CourseGroup"
          },
          "attenderGroup": {
            "$ref": "#/components/schemas/AttenderGroup"
          }
        },
        "additionalProperties": false
      },
      "CourseGroupUserAssigment": {
        "type": "object",
        "properties": {
          "courseGroupUserAssigmentId": {
            "type": "integer",
            "format": "int32"
          },
          "courseGroupId": {
            "type": "integer",
            "format": "int32"
          },
          "courseGroup": {
            "$ref": "#/components/schemas/CourseGroup"
          },
          "userId": {
            "type": "integer",
            "format": "int32",
            "nullable": true
          },
          "dateCreated": {
            "type": "string",
            "format": "date-time",
            "readOnly": true
          },
          "isExcluded": {
            "type": "boolean"
          },
          "user": {
            "$ref": "#/components/schemas/User"
          }
        },
        "additionalProperties": false
      },
      "CourseSession": {
        "type": "object",
        "properties": {
          "courseSessionId": {
            "type": "integer",
            "format": "int32"
          },
          "courseGroupId": {
            "type": "integer",
            "format": "int32"
          },
          "courseGroup": {
            "$ref": "#/components/schemas/CourseGroup"
          },
          "locationName": {
            "maxLength": 255,
            "type": "string"
          },
          "dateStart": {
            "type": "string",
            "format": "date-time"
          },
          "dateEnd": {
            "type": "string",
            "format": "date-time"
          },
          "dateCreated": {
            "type": "string",
            "format": "date-time",
            "readOnly": true
          },
          "attendanceLogs": {
            "type": "array",
            "items": {
              "$ref": "#/components/schemas/AttendanceLog"
            }
          }
        },
        "additionalProperties": false
      },
      "CourseSessionAttendanceRecord": {
        "type": "object",
        "properties": {
          "attendanceLogId": {
            "type": "integer",
            "format": "int32",
            "nullable": true
          },
          "courseSessionId": {
            "type": "integer",
            "format": "int32"
          },
          "attenderUserId": {
            "type": "integer",
            "format": "int32",
            "nullable": true
          },
          "userName": {
            "type": "string",
            "nullable": true
          },
          "userSurname": {
            "type": "string",
            "nullable": true
          },
          "studentAlbumIdNumber": {
            "type": "integer",
            "format": "int32",
            "nullable": true
          },
          "attendanceLogMinDateCreated": {
            "type": "string",
            "format": "date-time",
            "nullable": true
          },
          "wasUserPresent": {
            "type": "boolean",
            "readOnly": true
          }
        },
        "additionalProperties": false
      },
      "CourseSessionListFilters": {
        "type": "object",
        "properties": {
          "search": {
            "type": "string",
            "nullable": true
          },
          "courseName": {
            "type": "string",
            "nullable": true
          },
          "courseGroupName": {
            "type": "string",
            "nullable": true
          },
          "locationName": {
            "type": "string",
            "nullable": true
          },
          "dateStart": {
            "type": "string",
            "format": "date-time",
            "nullable": true
          },
          "dateEnd": {
            "type": "string",
            "format": "date-time",
            "nullable": true
          }
        },
        "additionalProperties": false
      },
      "CourseSessionListFiltersPagedListParams": {
        "required": [
          "pageNumber",
          "pageSize"
        ],
        "type": "object",
        "properties": {
          "pageNumber": {
            "type": "integer",
            "format": "int32"
          },
          "pageSize": {
            "type": "integer",
            "format": "int32"
          },
          "filters": {
            "$ref": "#/components/schemas/CourseSessionListFilters"
          },
          "sortBy": {
            "type": "string",
            "nullable": true
          }
        },
        "additionalProperties": false
      },
      "CourseSessionListItem": {
        "type": "object",
        "properties": {
          "courseId": {
            "type": "integer",
            "format": "int32",
            "readOnly": true
          },
          "courseName": {
            "type": "string",
            "readOnly": true
          },
          "courseGroupId": {
            "type": "integer",
            "format": "int32",
            "readOnly": true
          },
          "courseGroupName": {
            "type": "string",
            "readOnly": true
          },
          "courseSessionId": {
            "type": "integer",
            "format": "int32",
            "readOnly": true
          },
          "locationName": {
            "type": "string",
            "readOnly": true
          },
          "dateStart": {
            "type": "string",
            "format": "date-time",
            "readOnly": true
          },
          "dateEnd": {
            "type": "string",
            "format": "date-time",
            "readOnly": true
          }
        },
        "additionalProperties": false
      },
      "CourseSessionListItemPagedList": {
        "required": [
          "items",
          "pageNumber",
          "pageSize",
          "totalCount",
          "totalPages"
        ],
        "type": "object",
        "properties": {
          "items": {
            "type": "array",
            "items": {
              "$ref": "#/components/schemas/CourseSessionListItem"
            }
          },
          "totalCount": {
            "type": "integer",
            "format": "int32"
          },
          "pageNumber": {
            "type": "integer",
            "format": "int32"
          },
          "pageSize": {
            "type": "integer",
            "format": "int32"
          },
          "totalPages": {
            "type": "integer",
            "format": "int32",
            "readOnly": true
          }
        },
        "additionalProperties": false
      },
      "DeviceRegisterDTO": {
        "type": "object",
        "properties": {
          "deviceName": {
            "type": "string"
          },
          "studentName": {
            "type": "string"
          },
          "studentSurname": {
            "type": "string"
          },
          "albumIdNumber": {
            "type": "integer",
            "format": "int32"
          }
        },
        "additionalProperties": false
      },
      "ProblemDetails": {
        "type": "object",
        "properties": {
          "type": {
            "type": "string",
            "nullable": true
          },
          "title": {
            "type": "string",
            "nullable": true
          },
          "status": {
            "type": "integer",
            "format": "int32",
            "nullable": true
          },
          "detail": {
            "type": "string",
            "nullable": true
          },
          "instance": {
            "type": "string",
            "nullable": true
          }
        },
        "additionalProperties": { }
      },
      "Student": {
        "type": "object",
        "properties": {
          "studentId": {
            "type": "integer",
            "format": "int32"
          },
          "albumIdNumber": {
            "type": "integer",
            "format": "int32"
          },
          "currentYearOfStudy": {
            "type": "integer",
            "format": "int32"
          },
          "dateCreated": {
            "type": "string",
            "format": "date-time",
            "readOnly": true
          }
        },
        "additionalProperties": false
      },
      "StudentUserDTO": {
        "type": "object",
        "properties": {
          "userId": {
            "type": "integer",
            "format": "int32",
            "readOnly": true
          },
          "name": {
            "type": "string"
          },
          "surname": {
            "type": "string"
          },
          "albumIdNumber": {
            "type": "integer",
            "format": "int32"
          }
        },
        "additionalProperties": false
      },
      "Teacher": {
        "type": "object",
        "properties": {
          "teacherId": {
            "type": "integer",
            "format": "int32"
          },
          "academicTitle": {
            "maxLength": 255,
            "type": "string"
          },
          "dateCreated": {
            "type": "string",
            "format": "date-time",
            "readOnly": true
          }
        },
        "additionalProperties": false
      },
      "TeacherUserDTO": {
        "type": "object",
        "properties": {
          "userId": {
            "type": "integer",
            "format": "int32",
            "readOnly": true
          },
          "name": {
            "type": "string"
          },
          "surname": {
            "type": "string"
          },
          "academicTitle": {
            "type": "string"
          }
        },
        "additionalProperties": false
      },
      "TokenResult": {
        "type": "object",
        "properties": {
          "token": {
            "type": "string"
          },
          "expires": {
            "type": "string",
            "format": "date-time",
            "nullable": true
          }
        },
        "additionalProperties": false
      },
      "User": {
        "type": "object",
        "properties": {
          "userId": {
            "type": "integer",
            "format": "int32"
          },
          "loginName": {
            "type": "string"
          },
          "name": {
            "type": "string",
            "nullable": true
          },
          "surname": {
            "type": "string",
            "nullable": true
          },
          "studentId": {
            "type": "integer",
            "format": "int32",
            "nullable": true
          },
          "teacherId": {
            "type": "integer",
            "format": "int32",
            "nullable": true
          },
          "student": {
            "$ref": "#/components/schemas/Student"
          },
          "isStudent": {
            "type": "boolean",
            "readOnly": true
          },
          "teacher": {
            "$ref": "#/components/schemas/Teacher"
          },
          "isTeacher": {
            "type": "boolean",
            "readOnly": true
          },
          "dateCreated": {
            "type": "string",
            "format": "date-time",
            "readOnly": true
          },
          "deviceName": {
            "maxLength": 255,
            "type": "string",
            "nullable": true
          },
          "isAdmin": {
            "type": "boolean"
          }
        },
        "additionalProperties": false
      },
      "UserDTO": {
        "type": "object",
        "properties": {
          "userId": {
            "type": "integer",
            "format": "int32",
            "readOnly": true
          },
          "name": {
            "type": "string"
          },
          "surname": {
            "type": "string"
          }
        },
        "additionalProperties": false
      },
      "UserListFilters": {
        "type": "object",
        "properties": {
          "userId": {
            "type": "integer",
            "format": "int32",
            "nullable": true
          },
          "search": {
            "type": "string",
            "nullable": true
          },
          "isTeacher": {
            "type": "boolean",
            "nullable": true
          },
          "isStudent": {
            "type": "boolean",
            "nullable": true
          },
          "isAdmin": {
            "type": "boolean",
            "nullable": true
          },
          "dateCreatedStart": {
            "type": "string",
            "format": "date-time",
            "nullable": true
          },
          "dateCreatedEnd": {
            "type": "string",
            "format": "date-time",
            "nullable": true
          }
        },
        "additionalProperties": false
      },
      "UserListFiltersPagedListParams": {
        "required": [
          "pageNumber",
          "pageSize"
        ],
        "type": "object",
        "properties": {
          "pageNumber": {
            "type": "integer",
            "format": "int32"
          },
          "pageSize": {
            "type": "integer",
            "format": "int32"
          },
          "filters": {
            "$ref": "#/components/schemas/UserListFilters"
          },
          "sortBy": {
            "type": "string",
            "nullable": true
          }
        },
        "additionalProperties": false
      },
      "UserListItem": {
        "type": "object",
        "properties": {
          "userId": {
            "type": "integer",
            "format": "int32",
            "nullable": true
          },
          "loginName": {
            "type": "string",
            "nullable": true
          },
          "name": {
            "type": "string",
            "nullable": true
          },
          "surname": {
            "type": "string",
            "nullable": true
          },
          "studentId": {
            "type": "integer",
            "format": "int32",
            "nullable": true
          },
          "teacherId": {
            "type": "integer",
            "format": "int32",
            "nullable": true
          },
          "isStudent": {
            "type": "boolean",
            "readOnly": true
          },
          "isTeacher": {
            "type": "boolean",
            "readOnly": true
          },
          "isAdmin": {
            "type": "boolean"
          },
          "dateCreated": {
            "type": "string",
            "format": "date-time",
            "nullable": true
          }
        },
        "additionalProperties": false
      },
      "UserListItemPagedList": {
        "required": [
          "items",
          "pageNumber",
          "pageSize",
          "totalCount",
          "totalPages"
        ],
        "type": "object",
        "properties": {
          "items": {
            "type": "array",
            "items": {
              "$ref": "#/components/schemas/UserListItem"
            }
          },
          "totalCount": {
            "type": "integer",
            "format": "int32"
          },
          "pageNumber": {
            "type": "integer",
            "format": "int32"
          },
          "pageSize": {
            "type": "integer",
            "format": "int32"
          },
          "totalPages": {
            "type": "integer",
            "format": "int32",
            "readOnly": true
          }
        },
        "additionalProperties": false
      }
    },
    "securitySchemes": {
      "Bearer": {
        "type": "http",
        "description": "JWT Authorization header using the Bearer scheme. Example: \"Authorization: Bearer {token}\"",
        "scheme": "Bearer",
        "bearerFormat": "JWT"
      }
    }
  },
  "security": [
    {
      "Bearer": [ ]
    }
  ]
}